octopus_sdk/__init__.py
octopus_sdk/agent_sdk.py
octopus_sdk/kernel_sdk.py
octopus_sdk/utils.py
octopus_sdk-0.4.18.dist-info/METADATA
octopus_sdk-0.4.18.dist-info/WHEEL
octopus_sdk-0.4.18.dist-info/top_level.txt
octopus_sdk-0.4.18.dist-info/RECORD
