Metadata-Version: 2.1
Name: octopus-sdk
Version: 0.4.18
Summary: Open source code interpreter agent for LLM
Home-page: https://github.com/dbpunk-labs/octopus
Author: imotai
Author-email: wangtaize@dbpunk.com
Requires-Dist: octopus-proto
Requires-Dist: aiofiles
